<?xml version="1.0" encoding="utf-8"?>
<!DOCTYPE hibernate-mapping PUBLIC "-//Hibernate/Hibernate Mapping DTD 3.0//EN"
"http://hibernate.sourceforge.net/hibernate-mapping-3.0.dtd">
<!-- 
    Mapping file autogenerated by MyEclipse Persistence Tools
-->
<hibernate-mapping>
    <class name="com.zhidian.server.model.Order" table="t_order" catalog="zhidian">
        <id name="orderId" type="java.lang.String">
            <column name="order_id" />
            <generator class="assigned"></generator>
        </id>
        <property name="goodsId" type="java.lang.String">
            <column name="goods_id" not-null="true">
                <comment>商品ID</comment>
            </column>
        </property>
        <property name="orderPayWay" type="java.lang.Integer">
            <column name="order_pay_way" not-null="true">
                <comment>订单支付方式0:系统支付1:支付宝支付</comment>
            </column>
        </property>
        <property name="orderPayStatus" type="java.lang.Integer">
            <column name="order_pay_status" not-null="true">
                <comment>订单支付状态0:未支付1:已支付</comment>
            </column>
        </property>
        <property name="orderStatus" type="java.lang.Integer">
            <column name="order_status" not-null="true">
                <comment>订单状态0:未提交1:未支付2:已支付3:已完成4:已结束5:退单中6:已退单7:已取消</comment>
            </column>
        </property>
        <property name="orderMoney" type="java.lang.Double">
            <column name="order_money" precision="11" not-null="true">
                <comment>订单金额</comment>
            </column>
        </property>
        <property name="orderIsDelete" type="java.lang.Integer">
            <column name="order_is_delete" not-null="true">
                <comment>订单是否删除0:没有删除1:软删除（已经加入回收站）</comment>
            </column>
        </property>
    </class>
</hibernate-mapping>
