<?xml version="1.0" encoding="utf-8"?>
<!DOCTYPE hibernate-mapping PUBLIC "-//Hibernate/Hibernate Mapping DTD 3.0//EN"
"http://hibernate.sourceforge.net/hibernate-mapping-3.0.dtd">
<!-- 
    Mapping file autogenerated by MyEclipse Persistence Tools
-->
<hibernate-mapping>
    <class name="com.zhidian.server.model.Manager" table="t_manager" catalog="zhidian">
        <id name="managerId" type="java.lang.String">
            <column name="manager_id" />
            <generator class="uuid.hex"></generator>
        </id>
        <property name="managerName" type="java.lang.String">
            <column name="manager_name" not-null="true">
                <comment>用户名</comment>
            </column>
        </property>
        <property name="managerPassword" type="java.lang.String">
            <column name="manager_password" not-null="true">
                <comment>用户密码</comment>
            </column>
        </property>
        <property name="managerIsDelete" type="java.lang.Integer">
            <column name="manager_is_delete" not-null="true">
                <comment>管理员状态0:没有删除1:软删除（在回收站内）</comment>
            </column>
        </property>
    </class>
</hibernate-mapping>
